{
    "instaloader": {
        "node_type": "Post",
        "version": "4.2.10"
    },
    "node": {
        "__typename": "GraphVideo",
        "caption_is_edited": true,
        "comments_disabled": false,
        "dash_info": {
            "is_dash_eligible": false,
            "number_of_qualities": 0,
            "video_dash_manifest": null
        },
        "dimensions": {
            "height": 480,
            "width": 480
        },
        "display_resources": [
            {
                "config_height": 640,
                "config_width": 640,
                "src": "https://scontent-cdt1-1.cdninstagram.com/v/t51.2885-15/e35/56422484_117861142733857_4615569718199218100_n.jpg?_nc_ht=scontent-cdt1-1.cdninstagram.com&_nc_cat=101&_nc_ohc=otK2DINx-LgAX-ZD6gX&oh=54dbf1687d8c211f0cbf243aa0db49a2&oe=5E116E80"
            },
            {
                "config_height": 750,
                "config_width": 750,
                "src": "https://scontent-cdt1-1.cdninstagram.com/v/t51.2885-15/e35/56422484_117861142733857_4615569718199218100_n.jpg?_nc_ht=scontent-cdt1-1.cdninstagram.com&_nc_cat=101&_nc_ohc=otK2DINx-LgAX-ZD6gX&oh=54dbf1687d8c211f0cbf243aa0db49a2&oe=5E116E80"
            },
            {
                "config_height": 1080,
                "config_width": 1080,
                "src": "https://scontent-cdt1-1.cdninstagram.com/v/t51.2885-15/e35/56422484_117861142733857_4615569718199218100_n.jpg?_nc_ht=scontent-cdt1-1.cdninstagram.com&_nc_cat=101&_nc_ohc=otK2DINx-LgAX-ZD6gX&oh=54dbf1687d8c211f0cbf243aa0db49a2&oe=5E116E80"
            }
        ],
        "display_url": "https://scontent-cdt1-1.cdninstagram.com/v/t51.2885-15/e35/56422484_117861142733857_4615569718199218100_n.jpg?_nc_ht=scontent-cdt1-1.cdninstagram.com&_nc_cat=101&_nc_ohc=otK2DINx-LgAX-ZD6gX&oh=54dbf1687d8c211f0cbf243aa0db49a2&oe=5E116E80",
        "edge_media_preview_comment": {
            "count": 429,
            "edges": [
                {
                    "node": {
                        "created_at": 1573257579,
                        "did_report_as_spam": false,
                        "edge_liked_by": {
                            "count": 1
                        },
                        "id": "17851158373675894",
                        "owner": {
                            "id": "4152670744",
                            "is_verified": false,
                            "profile_pic_url": "https://scontent-cdt1-1.cdninstagram.com/v/t51.2885-19/s150x150/79978385_517744142422549_78550098530795520_n.jpg?_nc_ht=scontent-cdt1-1.cdninstagram.com&_nc_ohc=rz-vdNDYgOQAX9HMhbW&oh=b7a6139bfac35b85288e1960c4f41d37&oe=5E8D78E9",
                            "username": "el__price"
                        },
                        "text": "@milsmaunder",
                        "viewer_has_liked": false
                    }
                },
                {
                    "node": {
                        "created_at": 1576347165,
                        "did_report_as_spam": false,
                        "edge_liked_by": {
                            "count": 0
                        },
                        "id": "18118836703008016",
                        "owner": {
                            "id": "1511694687",
                            "is_verified": false,
                            "profile_pic_url": "https://scontent-cdt1-1.cdninstagram.com/v/t51.2885-19/s150x150/42003309_886599394883389_1551193714590744576_n.jpg?_nc_ht=scontent-cdt1-1.cdninstagram.com&_nc_ohc=3CcUltCaJEgAX9-MLF4&oh=5733f4a58cda60186c601b2c6c884ea4&oe=5EACC4F5",
                            "username": "kendalmustard"
                        },
                        "text": "@elliemabel",
                        "viewer_has_liked": false
                    }
                }
            ]
        },
        "edge_media_preview_like": {
            "count": 5862,
            "edges": []
        },
        "edge_media_to_caption": {
            "edges": [
                {
                    "node": {
                        "text": "Wishing you all have a lovely & relaxing Easter and Passover...@tablemannerspodcast Series 6 starts next week! #wednesdayistablemanners *wait til the end"
                    }
                }
            ]
        },
        "edge_media_to_comment": {
            "count": 429
        },
        "edge_media_to_parent_comment": {
            "count": 429,
            "edges": [
                {
                    "node": {
                        "created_at": 1557067055,
                        "did_report_as_spam": false,
                        "edge_liked_by": {
                            "count": 1
                        },
                        "edge_threaded_comments": {
                            "count": 0,
                            "edges": [],
                            "page_info": {
                                "end_cursor": null,
                                "has_next_page": false
                            }
                        },
                        "id": "17994933469223450",
                        "owner": {
                            "id": "420793062",
                            "is_verified": false,
                            "profile_pic_url": "https://scontent-cdt1-1.cdninstagram.com/v/t51.2885-19/s150x150/74897433_2481376628784172_4400533859809099776_n.jpg?_nc_ht=scontent-cdt1-1.cdninstagram.com&_nc_ohc=ReTnSA2obl4AX_L5RlC&oh=3494634f6f4dc8ce9f16bde023512ef5&oe=5EAE159C",
                            "username": "lozzamitchellw"
                        },
                        "text": "\ud83d\ude02\ud83d\ude02\ud83d\ude02",
                        "viewer_has_liked": false
                    }
                },
                {
                    "node": {
                        "created_at": 1557156631,
                        "did_report_as_spam": false,
                        "edge_liked_by": {
                            "count": 1
                        },
                        "edge_threaded_comments": {
                            "count": 0,
                            "edges": [],
                            "page_info": {
                                "end_cursor": null,
                                "has_next_page": false
                            }
                        },
                        "id": "17891079568325790",
                        "owner": {
                            "id": "5878867293",
                            "is_verified": false,
                            "profile_pic_url": "https://scontent-cdt1-1.cdninstagram.com/v/t51.2885-19/s150x150/52494647_618454848579534_3040314427220951040_n.jpg?_nc_ht=scontent-cdt1-1.cdninstagram.com&_nc_ohc=219XGTkPpDgAX9eePjW&oh=d14903386cd4ad564bd95ace20296449&oe=5EB04318",
                            "username": "thechordzmusic"
                        },
                        "text": "Great!",
                        "viewer_has_liked": false
                    }
                },
                {
                    "node": {
                        "created_at": 1557480208,
                        "did_report_as_spam": false,
                        "edge_liked_by": {
                            "count": 1
                        },
                        "edge_threaded_comments": {
                            "count": 1,
                            "edges": [
                                {
                                    "node": {
                                        "created_at": 1557480542,
                                        "did_report_as_spam": false,
                                        "edge_liked_by": {
                                            "count": 0
                                        },
                                        "id": "18063726550047858",
                                        "owner": {
                                            "id": "387271034",
                                            "is_verified": false,
                                            "profile_pic_url": "https://scontent-cdt1-1.cdninstagram.com/v/t51.2885-19/s150x150/40563747_1780344845354188_2344872261795708928_n.jpg?_nc_ht=scontent-cdt1-1.cdninstagram.com&_nc_ohc=plkh5AHg0vMAX-y_RHC&oh=aeb1dbac9c0f0ea6be3f45fadff19ba6&oe=5EA727E8",
                                            "username": "wintersarah__"
                                        },
                                        "text": "@pollywoollard Ahahaha yes literally LOLLLLED!!! Bloody love them!!!!",
                                        "viewer_has_liked": false
                                    }
                                }
                            ],
                            "page_info": {
                                "end_cursor": null,
                                "has_next_page": false
                            }
                        },
                        "id": "18023175568170395",
                        "owner": {
                            "id": "623162434",
                            "is_verified": false,
                            "profile_pic_url": "https://scontent-cdt1-1.cdninstagram.com/v/t51.2885-19/s150x150/16789262_1768724116780108_4493713746526470144_a.jpg?_nc_ht=scontent-cdt1-1.cdninstagram.com&_nc_ohc=BNXE9Hf15xsAX90ORdO&oh=b917487847a0efb89793998a0c73e63b&oe=5EA882FD",
                            "username": "pollywoollard"
                        },
                        "text": "@wintersarah__  have you seen this?? \ud83d\ude02\ud83d\ude02",
                        "viewer_has_liked": false
                    }
                },
                {
                    "node": {
                        "created_at": 1557512119,
                        "did_report_as_spam": false,
                        "edge_liked_by": {
                            "count": 0
                        },
                        "edge_threaded_comments": {
                            "count": 0,
                            "edges": [],
                            "page_info": {
                                "end_cursor": null,
                                "has_next_page": false
                            }
                        },
                        "id": "17851883179421630",
                        "owner": {
                            "id": "8781717029",
                            "is_verified": false,
                            "profile_pic_url": "https://scontent-cdt1-1.cdninstagram.com/v/t51.2885-19/s150x150/67650314_723316481457161_165044082672926720_n.jpg?_nc_ht=scontent-cdt1-1.cdninstagram.com&_nc_ohc=YF2808wVEv4AX_9HuLK&oh=c723af070d7a14dac69b9ab49176b5e3&oe=5E9DBF02",
                            "username": "amorepontosbylu"
                        },
                        "text": "\ud83d\ude06\ud83d\ude06\ud83d\ude06\ud83d\ude06\ud83d\ude06\ud83e\udd2d\ud83e\udd2d\ud83e\udd2d",
                        "viewer_has_liked": false
                    }
                },
                {
                    "node": {
                        "created_at": 1558046918,
                        "did_report_as_spam": false,
                        "edge_liked_by": {
                            "count": 0
                        },
                        "edge_threaded_comments": {
                            "count": 0,
                            "edges": [],
                            "page_info": {
                                "end_cursor": null,
                                "has_next_page": false
                            }
                        },
                        "id": "17946964672282035",
                        "owner": {
                            "id": "11052121",
                            "is_verified": false,
                            "profile_pic_url": "https://scontent-cdt1-1.cdninstagram.com/v/t51.2885-19/s150x150/20686778_283929808754754_4900096151845339136_a.jpg?_nc_ht=scontent-cdt1-1.cdninstagram.com&_nc_ohc=AmAtIQSFt5MAX9ph0Ut&oh=fcfa52cf138d676b9e0578c5bea3ec53&oe=5EB09D5C",
                            "username": "gemkim123"
                        },
                        "text": "@jakskimber \ud83d\ude02",
                        "viewer_has_liked": false
                    }
                },
                {
                    "node": {
                        "created_at": 1558452389,
                        "did_report_as_spam": false,
                        "edge_liked_by": {
                            "count": 2
                        },
                        "edge_threaded_comments": {
                            "count": 1,
                            "edges": [
                                {
                                    "node": {
                                        "created_at": 1558456946,
                                        "did_report_as_spam": false,
                                        "edge_liked_by": {
                                            "count": 0
                                        },
                                        "id": "17972082514258035",
                                        "owner": {
                                            "id": "25599603",
                                            "is_verified": false,
                                            "profile_pic_url": "https://scontent-cdt1-1.cdninstagram.com/v/t51.2885-19/s150x150/58409721_2235167286798119_8888435261453631488_n.jpg?_nc_ht=scontent-cdt1-1.cdninstagram.com&_nc_ohc=2GdcFHIFB9IAX8NXLiN&oh=95e883279f416623866da0ddcc9707c5&oe=5EA6D07C",
                                            "username": "jamesnorbury"
                                        },
                                        "text": "@joshcorley hahaha i saw this before",
                                        "viewer_has_liked": false
                                    }
                                }
                            ],
                            "page_info": {
                                "end_cursor": null,
                                "has_next_page": false
                            }
                        },
                        "id": "17851637413434225",
                        "owner": {
                            "id": "6144427",
                            "is_verified": false,
                            "profile_pic_url": "https://scontent-cdt1-1.cdninstagram.com/v/t51.2885-19/s150x150/72228003_424988021712418_3220773044440006656_n.jpg?_nc_ht=scontent-cdt1-1.cdninstagram.com&_nc_ohc=5oFcpynHA_oAX-2ueHT&oh=ce3031075652a5e846b3142981cbb994&oe=5EA3E61F",
                            "username": "joshcorley"
                        },
                        "text": "@jamesnorbury",
                        "viewer_has_liked": false
                    }
                },
                {
                    "node": {
                        "created_at": 1559302484,
                        "did_report_as_spam": false,
                        "edge_liked_by": {
                            "count": 1
                        },
                        "edge_threaded_comments": {
                            "count": 0,
                            "edges": [],
                            "page_info": {
                                "end_cursor": null,
                                "has_next_page": false
                            }
                        },
                        "id": "17878106584366827",
                        "owner": {
                            "id": "470300692",
                            "is_verified": false,
                            "profile_pic_url": "https://scontent-cdt1-1.cdninstagram.com/v/t51.2885-19/10729283_1558613247702312_2011634422_a.jpg?_nc_ht=scontent-cdt1-1.cdninstagram.com&_nc_ohc=xNqB-o4S1SwAX-4l24a&oh=a19a9b3f20ed13dc69aa5b593e9b5212&oe=5EABC0EF",
                            "username": "egumina"
                        },
                        "text": "@simone_lyds  HAHA",
                        "viewer_has_liked": false
                    }
                },
                {
                    "node": {
                        "created_at": 1559488383,
                        "did_report_as_spam": false,
                        "edge_liked_by": {
                            "count": 0
                        },
                        "edge_threaded_comments": {
                            "count": 0,
                            "edges": [],
                            "page_info": {
                                "end_cursor": null,
                                "has_next_page": false
                            }
                        },
                        "id": "18003364252221966",
                        "owner": {
                            "id": "989215004",
                            "is_verified": false,
                            "profile_pic_url": "https://scontent-cdt1-1.cdninstagram.com/v/t51.2885-19/s150x150/67428291_394193814619654_8546674921185476608_n.jpg?_nc_ht=scontent-cdt1-1.cdninstagram.com&_nc_ohc=frdlqdhedjcAX8Kr8VB&oh=c0e4e2c430de7988c41e4268e88b5063&oe=5E975233",
                            "username": "laryh_wolf"
                        },
                        "text": "\ud83d\ude02\ud83d\ude02\ud83d\ude02\ud83d\ude02\ud83d\ude02",
                        "viewer_has_liked": false
                    }
                },
                {
                    "node": {
                        "created_at": 1559501284,
                        "did_report_as_spam": false,
                        "edge_liked_by": {
                            "count": 0
                        },
                        "edge_threaded_comments": {
                            "count": 0,
                            "edges": [],
                            "page_info": {
                                "end_cursor": null,
                                "has_next_page": false
                            }
                        },
                        "id": "18043618099142475",
                        "owner": {
                            "id": "825060494",
                            "is_verified": false,
                            "profile_pic_url": "https://scontent-cdt1-1.cdninstagram.com/v/t51.2885-19/s150x150/12912669_1118725798149254_818562906_a.jpg?_nc_ht=scontent-cdt1-1.cdninstagram.com&_nc_ohc=27UxcTo5GBIAX9Wvb8C&oh=9b2194c52fec0559fb1c33dcc7d8879a&oe=5EA0A176",
                            "username": "kon2re"
                        },
                        "text": "Hahahaha this is hilarious \ud83d\ude02\ud83d\ude02\ud83d\ude02",
                        "viewer_has_liked": false
                    }
                },
                {
                    "node": {
                        "created_at": 1559507848,
                        "did_report_as_spam": false,
                        "edge_liked_by": {
                            "count": 0
                        },
                        "edge_threaded_comments": {
                            "count": 0,
                            "edges": [],
                            "page_info": {
                                "end_cursor": null,
                                "has_next_page": false
                            }
                        },
                        "id": "17977496890253234",
                        "owner": {
                            "id": "1397175",
                            "is_verified": false,
                            "profile_pic_url": "https://scontent-cdt1-1.cdninstagram.com/v/t51.2885-19/s150x150/19436491_633440866851424_594824026711392256_a.jpg?_nc_ht=scontent-cdt1-1.cdninstagram.com&_nc_ohc=dZ2vUOsKiVAAX8SqM9W&oh=9cb9e57b10b068eaee97985d4af8800e&oe=5EA6F1DC",
                            "username": "josephine_elise"
                        },
                        "text": "@gracepurvis",
                        "viewer_has_liked": false
                    }
                },
                {
                    "node": {
                        "created_at": 1559560525,
                        "did_report_as_spam": false,
                        "edge_liked_by": {
                            "count": 1
                        },
                        "edge_threaded_comments": {
                            "count": 1,
                            "edges": [
                                {
                                    "node": {
                                        "created_at": 1559642301,
                                        "did_report_as_spam": false,
                                        "edge_liked_by": {
                                            "count": 0
                                        },
                                        "id": "17953656394280261",
                                        "owner": {
                                            "id": "4083157",
                                            "is_verified": false,
                                            "profile_pic_url": "https://scontent-cdt1-1.cdninstagram.com/v/t51.2885-19/s150x150/70275440_392492355033355_7766529094375702528_n.jpg?_nc_ht=scontent-cdt1-1.cdninstagram.com&_nc_ohc=xUxA0yPJZMAAX-sax0N&oh=3e04b808aeb64ec89d4223f07fc0a2c1&oe=5E8F5C26",
                                            "username": "katiejanenguyen"
                                        },
                                        "text": "@tanithsasha \ud83d\ude02",
                                        "viewer_has_liked": false
                                    }
                                }
                            ],
                            "page_info": {
                                "end_cursor": null,
                                "has_next_page": false
                            }
                        },
                        "id": "18037173775152954",
                        "owner": {
                            "id": "357251227",
                            "is_verified": false,
                            "profile_pic_url": "https://scontent-cdt1-1.cdninstagram.com/v/t51.2885-19/s150x150/38081851_521966511579789_8436259923414745088_n.jpg?_nc_ht=scontent-cdt1-1.cdninstagram.com&_nc_ohc=FK9bswlmozUAX-VEb5y&oh=2dff22ac2b0ca1e2923d11f2cbba7d6f&oe=5EAA5056",
                            "username": "tanithsasha"
                        },
                        "text": "@katiejanenguyen watch to the end \ud83d\ude02\ud83d\ude02\ud83d\ude02",
                        "viewer_has_liked": false
                    }
                },
                {
                    "node": {
                        "created_at": 1559851597,
                        "did_report_as_spam": false,
                        "edge_liked_by": {
                            "count": 1
                        },
                        "edge_threaded_comments": {
                            "count": 0,
                            "edges": [],
                            "page_info": {
                                "end_cursor": null,
                                "has_next_page": false
                            }
                        },
                        "id": "17859698140423979",
                        "owner": {
                            "id": "232228465",
                            "is_verified": false,
                            "profile_pic_url": "https://scontent-cdt1-1.cdninstagram.com/v/t51.2885-19/s150x150/77274724_1055648964827211_2305316111215755264_n.jpg?_nc_ht=scontent-cdt1-1.cdninstagram.com&_nc_ohc=b9z6b8uri2MAX9wL4Iq&oh=6e50c863f9f19c98d0add89eeb252b89&oe=5E998802",
                            "username": "indiaweir"
                        },
                        "text": "@debbie.weir wait until the end \ud83d\ude02\ud83d\ude02",
                        "viewer_has_liked": false
                    }
                },
                {
                    "node": {
                        "created_at": 1559902979,
                        "did_report_as_spam": false,
                        "edge_liked_by": {
                            "count": 0
                        },
                        "edge_threaded_comments": {
                            "count": 0,
                            "edges": [],
                            "page_info": {
                                "end_cursor": null,
                                "has_next_page": false
                            }
                        },
                        "id": "17970763168266185",
                        "owner": {
                            "id": "1695267745",
                            "is_verified": false,
                            "profile_pic_url": "https://scontent-cdt1-1.cdninstagram.com/v/t51.2885-19/10946632_1553774244869606_372639476_a.jpg?_nc_ht=scontent-cdt1-1.cdninstagram.com&_nc_ohc=aIDgTP5k2e4AX9wSdEC&oh=9a7c459cce07a61f5cdde4daf0916342&oe=5E9256B1",
                            "username": "debbie.weir"
                        },
                        "text": "\ud83e\udd23\ud83e\udd23\ud83e\udd23",
                        "viewer_has_liked": false
                    }
                },
                {
                    "node": {
                        "created_at": 1560199707,
                        "did_report_as_spam": false,
                        "edge_liked_by": {
                            "count": 0
                        },
                        "edge_threaded_comments": {
                            "count": 0,
                            "edges": [],
                            "page_info": {
                                "end_cursor": null,
                                "has_next_page": false
                            }
                        },
                        "id": "18046856080094107",
                        "owner": {
                            "id": "304119161",
                            "is_verified": false,
                            "profile_pic_url": "https://scontent-cdt1-1.cdninstagram.com/v/t51.2885-19/11848968_915611705153720_172205474_a.jpg?_nc_ht=scontent-cdt1-1.cdninstagram.com&_nc_ohc=9nLvsToTXvYAX97Ydeu&oh=f0861851b4ed389d49f9b9d28d47f6b0&oe=5EA3224A",
                            "username": "siobhanacus"
                        },
                        "text": "@emertumulty \ud83d\ude02\ud83d\ude02",
                        "viewer_has_liked": false
                    }
                },
                {
                    "node": {
                        "created_at": 1560698987,
                        "did_report_as_spam": false,
                        "edge_liked_by": {
                            "count": 0
                        },
                        "edge_threaded_comments": {
                            "count": 0,
                            "edges": [],
                            "page_info": {
                                "end_cursor": null,
                                "has_next_page": false
                            }
                        },
                        "id": "18078122704016268",
                        "owner": {
                            "id": "1535478647",
                            "is_verified": false,
                            "profile_pic_url": "https://scontent-cdt1-1.cdninstagram.com/v/t51.2885-19/s150x150/23824923_1593750007359639_1140746560812875776_n.jpg?_nc_ht=scontent-cdt1-1.cdninstagram.com&_nc_ohc=HxWmzPkNYrQAX-T6qTH&oh=78496f08402848e5a7d533fa2e2380f7&oe=5EA8D1E0",
                            "username": "dappadontravels"
                        },
                        "text": "\ud83d\ude02\ud83d\ude02\ud83d\ude02\ud83d\ude02",
                        "viewer_has_liked": false
                    }
                },
                {
                    "node": {
                        "created_at": 1560973947,
                        "did_report_as_spam": false,
                        "edge_liked_by": {
                            "count": 0
                        },
                        "edge_threaded_comments": {
                            "count": 1,
                            "edges": [
                                {
                                    "node": {
                                        "created_at": 1561145127,
                                        "did_report_as_spam": false,
                                        "edge_liked_by": {
                                            "count": 0
                                        },
                                        "id": "17910627997309108",
                                        "owner": {
                                            "id": "234094863",
                                            "is_verified": false,
                                            "profile_pic_url": "https://scontent-cdt1-1.cdninstagram.com/v/t51.2885-19/s150x150/54512018_1260045727482505_4685552601150783488_n.jpg?_nc_ht=scontent-cdt1-1.cdninstagram.com&_nc_ohc=X2wWJunfWCMAX-UuPT1&oh=aec9307d6c1befb0af6cf463758af829&oe=5EA8DBB7",
                                            "username": "smallone_3"
                                        },
                                        "text": "@just_emily684 haha oh god!",
                                        "viewer_has_liked": false
                                    }
                                }
                            ],
                            "page_info": {
                                "end_cursor": null,
                                "has_next_page": false
                            }
                        },
                        "id": "17855000878446311",
                        "owner": {
                            "id": "192383625",
                            "is_verified": false,
                            "profile_pic_url": "https://scontent-cdt1-1.cdninstagram.com/v/t51.2885-19/s150x150/60645105_320875605493077_4621294912535527424_n.jpg?_nc_ht=scontent-cdt1-1.cdninstagram.com&_nc_ohc=tp1z-C-oFucAX96sGAh&oh=0ba6aeac96486cb216ae0ae1973fcab5&oe=5E9BC0FD",
                            "username": "just_emily684"
                        },
                        "text": "@smallone_3 I'm finding this hilarious. \"it's burnt fucking cream mum!\"",
                        "viewer_has_liked": false
                    }
                },
                {
                    "node": {
                        "created_at": 1563367693,
                        "did_report_as_spam": false,
                        "edge_liked_by": {
                            "count": 0
                        },
                        "edge_threaded_comments": {
                            "count": 0,
                            "edges": [],
                            "page_info": {
                                "end_cursor": null,
                                "has_next_page": false
                            }
                        },
                        "id": "18001330441243880",
                        "owner": {
                            "id": "15977231",
                            "is_verified": false,
                            "profile_pic_url": "https://scontent-cdt1-1.cdninstagram.com/v/t51.2885-19/s150x150/79738268_1253363218205352_8731743769184960512_n.jpg?_nc_ht=scontent-cdt1-1.cdninstagram.com&_nc_ohc=ypRCXgNoPJIAX-xBFAJ&oh=73a4253af6164e0ba477cfb6aa88cdb5&oe=5EAA36CC",
                            "username": "katiemccracken23"
                        },
                        "text": "@angelamcc01 watch til the end \ud83e\udd23\ud83e\udd23\ud83e\udd23",
                        "viewer_has_liked": false
                    }
                },
                {
                    "node": {
                        "created_at": 1566340461,
                        "did_report_as_spam": false,
                        "edge_liked_by": {
                            "count": 1
                        },
                        "edge_threaded_comments": {
                            "count": 1,
                            "edges": [
                                {
                                    "node": {
                                        "created_at": 1566375640,
                                        "did_report_as_spam": false,
                                        "edge_liked_by": {
                                            "count": 0
                                        },
                                        "id": "17847256402577825",
                                        "owner": {
                                            "id": "368981609",
                                            "is_verified": false,
                                            "profile_pic_url": "https://scontent-cdt1-1.cdninstagram.com/v/t51.2885-19/s150x150/72218324_705009846643233_4967646495533694976_n.jpg?_nc_ht=scontent-cdt1-1.cdninstagram.com&_nc_ohc=EenLdMuWjYEAX-PiV8c&oh=395d9fe8b0c72fa6a6b9bfb672763fbb&oe=5E94223B",
                                            "username": "ktmcv"
                                        },
                                        "text": "@aislinglavery \ud83d\ude02\ud83d\ude02\ud83d\ude02",
                                        "viewer_has_liked": false
                                    }
                                }
                            ],
                            "page_info": {
                                "end_cursor": null,
                                "has_next_page": false
                            }
                        },
                        "id": "18093814744019251",
                        "owner": {
                            "id": "276493489",
                            "is_verified": false,
                            "profile_pic_url": "https://scontent-cdt1-1.cdninstagram.com/v/t51.2885-19/s150x150/69747308_409408646668991_5282377481326690304_n.jpg?_nc_ht=scontent-cdt1-1.cdninstagram.com&_nc_ohc=8zlFNyEJOwoAX-Vy8tX&oh=f8f77fcaddd6789fa50e5536fa0e8c60&oe=5E94F719",
                            "username": "aislinglavery"
                        },
                        "text": "@ktmcv this",
                        "viewer_has_liked": false
                    }
                },
                {
                    "node": {
                        "created_at": 1567860506,
                        "did_report_as_spam": false,
                        "edge_liked_by": {
                            "count": 0
                        },
                        "edge_threaded_comments": {
                            "count": 0,
                            "edges": [],
                            "page_info": {
                                "end_cursor": null,
                                "has_next_page": false
                            }
                        },
                        "id": "17917983211333109",
                        "owner": {
                            "id": "1422157638",
                            "is_verified": false,
                            "profile_pic_url": "https://scontent-cdt1-1.cdninstagram.com/v/t51.2885-19/s150x150/78840265_576414309882699_8370121923887104000_n.jpg?_nc_ht=scontent-cdt1-1.cdninstagram.com&_nc_ohc=7fWTCyPXyJAAX_oLy3Z&oh=b5056a0ed859411b8d786904638fadd6&oe=5EA8E6C6",
                            "username": "nataschaniebauer"
                        },
                        "text": "\ud83d\ude02\ud83d\ude02\ud83d\ude02\ud83d\ude02\ud83d\ude02\ud83d\ude02",
                        "viewer_has_liked": false
                    }
                },
                {
                    "node": {
                        "created_at": 1570552397,
                        "did_report_as_spam": false,
                        "edge_liked_by": {
                            "count": 0
                        },
                        "edge_threaded_comments": {
                            "count": 0,
                            "edges": [],
                            "page_info": {
                                "end_cursor": null,
                                "has_next_page": false
                            }
                        },
                        "id": "18103913470063305",
                        "owner": {
                            "id": "4531765641",
                            "is_verified": false,
                            "profile_pic_url": "https://scontent-cdt1-1.cdninstagram.com/v/t51.2885-19/s150x150/67594738_336376520604567_8718077007155429376_n.jpg?_nc_ht=scontent-cdt1-1.cdninstagram.com&_nc_ohc=vHIL00ne1_4AX9JAk1v&oh=1f32e992e3c89551f6822a92d8299d24&oe=5EAB2513",
                            "username": "sitze_am_meer"
                        },
                        "text": "\ud83d\ude02\ud83d\ude02\ud83d\ude02",
                        "viewer_has_liked": false
                    }
                },
                {
                    "node": {
                        "created_at": 1571186377,
                        "did_report_as_spam": false,
                        "edge_liked_by": {
                            "count": 0
                        },
                        "edge_threaded_comments": {
                            "count": 0,
                            "edges": [],
                            "page_info": {
                                "end_cursor": null,
                                "has_next_page": false
                            }
                        },
                        "id": "17842336660739346",
                        "owner": {
                            "id": "5583860207",
                            "is_verified": false,
                            "profile_pic_url": "https://scontent-cdt1-1.cdninstagram.com/v/t51.2885-19/s150x150/46640290_785004815201604_530057504730644480_n.jpg?_nc_ht=scontent-cdt1-1.cdninstagram.com&_nc_ohc=8RwyBzrDrMsAX_JUk9D&oh=c6ed2f181155adb85ee1e738978b69c9&oe=5E9383A8",
                            "username": "jack_m_c"
                        },
                        "text": "@vjissurey lol",
                        "viewer_has_liked": false
                    }
                },
                {
                    "node": {
                        "created_at": 1571859830,
                        "did_report_as_spam": false,
                        "edge_liked_by": {
                            "count": 0
                        },
                        "edge_threaded_comments": {
                            "count": 0,
                            "edges": [],
                            "page_info": {
                                "end_cursor": null,
                                "has_next_page": false
                            }
                        },
                        "id": "17857754842585847",
                        "owner": {
                            "id": "13943904",
                            "is_verified": false,
                            "profile_pic_url": "https://scontent-cdt1-1.cdninstagram.com/v/t51.2885-19/s150x150/66639723_587375628336162_4032117934594719744_n.jpg?_nc_ht=scontent-cdt1-1.cdninstagram.com&_nc_ohc=hiN-brIPp9UAX9pXDVP&oh=f4e668af64af2f43ad8bf7da32353a17&oe=5E985059",
                            "username": "indiatianeex"
                        },
                        "text": "@charlotte_1993 a little taster it\u2019s sooo good \ud83e\udd23",
                        "viewer_has_liked": false
                    }
                },
                {
                    "node": {
                        "created_at": 1573257579,
                        "did_report_as_spam": false,
                        "edge_liked_by": {
                            "count": 1
                        },
                        "edge_threaded_comments": {
                            "count": 0,
                            "edges": [],
                            "page_info": {
                                "end_cursor": null,
                                "has_next_page": false
                            }
                        },
                        "id": "17851158373675894",
                        "owner": {
                            "id": "4152670744",
                            "is_verified": false,
                            "profile_pic_url": "https://scontent-cdt1-1.cdninstagram.com/v/t51.2885-19/s150x150/79978385_517744142422549_78550098530795520_n.jpg?_nc_ht=scontent-cdt1-1.cdninstagram.com&_nc_ohc=rz-vdNDYgOQAX9HMhbW&oh=b7a6139bfac35b85288e1960c4f41d37&oe=5E8D78E9",
                            "username": "el__price"
                        },
                        "text": "@milsmaunder",
                        "viewer_has_liked": false
                    }
                },
                {
                    "node": {
                        "created_at": 1576347165,
                        "did_report_as_spam": false,
                        "edge_liked_by": {
                            "count": 0
                        },
                        "edge_threaded_comments": {
                            "count": 0,
                            "edges": [],
                            "page_info": {
                                "end_cursor": null,
                                "has_next_page": false
                            }
                        },
                        "id": "18118836703008016",
                        "owner": {
                            "id": "1511694687",
                            "is_verified": false,
                            "profile_pic_url": "https://scontent-cdt1-1.cdninstagram.com/v/t51.2885-19/s150x150/42003309_886599394883389_1551193714590744576_n.jpg?_nc_ht=scontent-cdt1-1.cdninstagram.com&_nc_ohc=3CcUltCaJEgAX9-MLF4&oh=5733f4a58cda60186c601b2c6c884ea4&oe=5EACC4F5",
                            "username": "kendalmustard"
                        },
                        "text": "@elliemabel",
                        "viewer_has_liked": false
                    }
                }
            ],
            "page_info": {
                "end_cursor": "QVFEOXBjY0plX2YxSkp0aTlXSGUwYmNmZ2ZvTUhtZDJXeUgtYXMtd3RNTFd3LXJxb2s2eDRWaWJjMVBiOEtzNV81OXRHNTYtWFBWYnZTRnRTNGhBSXJneQ==",
                "has_next_page": true
            }
        },
        "edge_media_to_sponsor_user": {
            "edges": []
        },
        "edge_media_to_tagged_user": {
            "edges": [
                {
                    "node": {
                        "user": {
                            "full_name": "",
                            "id": "7988206579",
                            "is_verified": true,
                            "profile_pic_url": "https://scontent-cdt1-1.cdninstagram.com/v/t51.2885-19/s150x150/34856352_459495674500247_2484371760187703296_n.jpg?_nc_ht=scontent-cdt1-1.cdninstagram.com&_nc_ohc=tC3vgu5aQIoAX-FcBmF&oh=005684f166d8fbdb0572f7812d07d57a&oe=5E9258B9",
                            "username": "tablemannerspodcast"
                        },
                        "x": 0.0,
                        "y": 0.0
                    }
                }
            ]
        },
        "edge_web_media_to_related_media": {
            "edges": []
        },
        "encoding_status": null,
        "fact_check_information": null,
        "fact_check_overall_rating": null,
        "gating_info": null,
        "has_ranked_comments": false,
        "id": "2026297009926611249",
        "is_ad": false,
        "is_published": true,
        "is_video": true,
        "location": null,
        "media_preview": "ACoqr3V7OtxIqyMArEAelV21C4B4kb9P8Kg1Bit1Jj+8aqq/zZbkUirqxsLe3BIJdsY9R1/KtBbiUj7xrDDg9O3atqMZA+lSPQk8+U9GNbUedoz1wP5Vkqta69B9KpEs4PUf+PmT/eNUxWzdqhuJM9dxqmlsZpNsQz/IUrjtpcijXH9a3I5doAPtVd9Nlh5OCCO1P8k/KVOeMH1zU3KSNNTWsvQfQVzwkcD7uRXQRnKg+w/lVogz5bCCSQyPyc81NGIoR+7UD6Vb2j0FGxT2H5VFijOkkWRSv5VmlOAS2GPaui8tPQfkKTyk67R+QoSsO5iQRyjJ7e/etxPujPoKXaPQU6rRDP/Z",
        "owner": {
            "biography": "I eat and sing and have a podcast called Table Manners.",
            "blocked_by_viewer": false,
            "business_category_name": "Creators & Celebrities",
            "connected_fb_page": null,
            "country_block": false,
            "edge_felix_video_timeline": {
                "count": 0,
                "edges": [],
                "page_info": {
                    "end_cursor": null,
                    "has_next_page": false
                }
            },
            "edge_follow": {
                "count": 2528
            },
            "edge_followed_by": {
                "count": 278901
            },
            "edge_mutual_followed_by": {
                "count": 0,
                "edges": []
            },
            "external_url": null,
            "external_url_linkshimmed": null,
            "followed_by_viewer": false,
            "follows_viewer": false,
            "full_name": "Jessie Ware",
            "has_blocked_viewer": false,
            "has_channel": false,
            "has_requested_viewer": false,
            "highlight_reel_count": 0,
            "id": "13500861",
            "is_business_account": true,
            "is_joined_recently": false,
            "is_private": false,
            "is_verified": true,
            "profile_pic_url": "https://scontent-cdt1-1.cdninstagram.com/v/t51.2885-19/s150x150/21827580_1726514424311245_3410729032646393856_n.jpg?_nc_ht=scontent-cdt1-1.cdninstagram.com&_nc_ohc=TZzPdg--groAX93JMYe&oh=82f2340ae3afd8affbd8561525fa262a&oe=5EAA1279",
            "profile_pic_url_hd": "https://scontent-cdt1-1.cdninstagram.com/v/t51.2885-19/s320x320/21827580_1726514424311245_3410729032646393856_n.jpg?_nc_ht=scontent-cdt1-1.cdninstagram.com&_nc_ohc=TZzPdg--groAX93JMYe&oh=a276feb34265329f713b229f1da16ded&oe=5EA8AD01",
            "requested_by_viewer": false,
            "username": "jessieware"
        },
        "product_type": "feed",
        "shortcode": "Bwe2mUOHKEx",
        "taken_at_timestamp": 1555773594,
        "thumbnail_resources": [
            {
                "config_height": 150,
                "config_width": 150,
                "src": "https://scontent-cdt1-1.cdninstagram.com/v/t51.2885-15/e35/s150x150/56422484_117861142733857_4615569718199218100_n.jpg?_nc_ht=scontent-cdt1-1.cdninstagram.com&_nc_cat=101&_nc_ohc=otK2DINx-LgAX-ZD6gX&oh=8fafa917a28f09a0a7224cf4ecbee326&oe=5E120642"
            },
            {
                "config_height": 240,
                "config_width": 240,
                "src": "https://scontent-cdt1-1.cdninstagram.com/v/t51.2885-15/e35/s240x240/56422484_117861142733857_4615569718199218100_n.jpg?_nc_ht=scontent-cdt1-1.cdninstagram.com&_nc_cat=101&_nc_ohc=otK2DINx-LgAX-ZD6gX&oh=7b2b41bb25c2367d4ff474657ddd9e1e&oe=5E117FC8"
            },
            {
                "config_height": 320,
                "config_width": 320,
                "src": "https://scontent-cdt1-1.cdninstagram.com/v/t51.2885-15/e35/s320x320/56422484_117861142733857_4615569718199218100_n.jpg?_nc_ht=scontent-cdt1-1.cdninstagram.com&_nc_cat=101&_nc_ohc=otK2DINx-LgAX-ZD6gX&oh=66fc6d933edd2629f094256c8e3d1b54&oe=5E11FC32"
            },
            {
                "config_height": 480,
                "config_width": 480,
                "src": "https://scontent-cdt1-1.cdninstagram.com/v/t51.2885-15/e35/56422484_117861142733857_4615569718199218100_n.jpg?_nc_ht=scontent-cdt1-1.cdninstagram.com&_nc_cat=101&_nc_ohc=otK2DINx-LgAX-ZD6gX&oh=54dbf1687d8c211f0cbf243aa0db49a2&oe=5E116E80"
            },
            {
                "config_height": 640,
                "config_width": 640,
                "src": "https://scontent-cdt1-1.cdninstagram.com/v/t51.2885-15/e35/56422484_117861142733857_4615569718199218100_n.jpg?_nc_ht=scontent-cdt1-1.cdninstagram.com&_nc_cat=101&_nc_ohc=otK2DINx-LgAX-ZD6gX&oh=54dbf1687d8c211f0cbf243aa0db49a2&oe=5E116E80"
            }
        ],
        "thumbnail_src": "https://scontent-cdt1-1.cdninstagram.com/v/t51.2885-15/e35/56422484_117861142733857_4615569718199218100_n.jpg?_nc_ht=scontent-cdt1-1.cdninstagram.com&_nc_cat=101&_nc_ohc=otK2DINx-LgAX-ZD6gX&oh=54dbf1687d8c211f0cbf243aa0db49a2&oe=5E116E80",
        "title": "",
        "tracking_token": "eyJ2ZXJzaW9uIjo1LCJwYXlsb2FkIjp7ImlzX2FuYWx5dGljc190cmFja2VkIjp0cnVlLCJ1dWlkIjoiYzg4MWE0MDI0NWQxNDBkMWJjODk0YWQxNTkwODY5ZWIyMDI2Mjk3MDA5OTI2NjExMjQ5In0sInNpZ25hdHVyZSI6IiJ9",
        "video_duration": 32.63,
        "video_url": "https://scontent-cdt1-1.cdninstagram.com/v/t50.2886-16/58344357_888616588150113_6784732229441421312_n.mp4?_nc_ht=scontent-cdt1-1.cdninstagram.com&_nc_cat=109&_nc_ohc=niX2eZ6HoAoAX_e_iXZ&oe=5E124BA7&oh=9536e421b3c19e1c06cddb165dad0a9f",
        "video_view_count": 50297,
        "viewer_can_reshare": true,
        "viewer_has_liked": false,
        "viewer_has_saved": false,
        "viewer_has_saved_to_collection": false,
        "viewer_in_photo_of_you": false
    }
}