{
    "instaloader": {
        "node_type": "Post",
        "version": "4.2.10"
    },
    "node": {
        "__typename": "GraphImage",
        "accessibility_caption": "Image may contain: one or more people, people standing, food and indoor",
        "caption_is_edited": true,
        "comments_disabled": false,
        "dimensions": {
            "height": 750,
            "width": 750
        },
        "display_resources": [
            {
                "config_height": 640,
                "config_width": 640,
                "src": "https://scontent-cdt1-1.cdninstagram.com/v/t51.2885-15/e15/s640x640/72549021_1414349085380197_1862529061723404970_n.jpg?_nc_ht=scontent-cdt1-1.cdninstagram.com&_nc_cat=101&_nc_ohc=aZJw_96Wy2UAX_V4oVv&oh=cded10e99717ad8b9c19ab9a9fad0d18&oe=5E987B68"
            },
            {
                "config_height": 750,
                "config_width": 750,
                "src": "https://scontent-cdt1-1.cdninstagram.com/v/t51.2885-15/e15/72549021_1414349085380197_1862529061723404970_n.jpg?_nc_ht=scontent-cdt1-1.cdninstagram.com&_nc_cat=101&_nc_ohc=aZJw_96Wy2UAX_V4oVv&oh=87e1b83011dcd6b8867c7cd8beb49383&oe=5EAD5D40"
            },
            {
                "config_height": 1080,
                "config_width": 1080,
                "src": "https://scontent-cdt1-1.cdninstagram.com/v/t51.2885-15/e15/72549021_1414349085380197_1862529061723404970_n.jpg?_nc_ht=scontent-cdt1-1.cdninstagram.com&_nc_cat=101&_nc_ohc=aZJw_96Wy2UAX_V4oVv&oh=87e1b83011dcd6b8867c7cd8beb49383&oe=5EAD5D40"
            }
        ],
        "display_url": "https://scontent-cdt1-1.cdninstagram.com/v/t51.2885-15/e15/72549021_1414349085380197_1862529061723404970_n.jpg?_nc_ht=scontent-cdt1-1.cdninstagram.com&_nc_cat=101&_nc_ohc=aZJw_96Wy2UAX_V4oVv&oh=87e1b83011dcd6b8867c7cd8beb49383&oe=5EAD5D40",
        "edge_media_preview_comment": {
            "count": 57,
            "edges": [
                {
                    "node": {
                        "created_at": 1573109340,
                        "did_report_as_spam": false,
                        "edge_liked_by": {
                            "count": 0
                        },
                        "id": "17849526832696850",
                        "owner": {
                            "id": "23233786449",
                            "is_verified": false,
                            "profile_pic_url": "https://scontent-cdt1-1.cdninstagram.com/v/t51.2885-19/s150x150/74607448_2429343810658964_7115666447510011904_n.jpg?_nc_ht=scontent-cdt1-1.cdninstagram.com&_nc_ohc=xx8Xypt_BS8AX8QdCme&oh=4a94c4f4a39c9f75ebc67617cc28ea57&oe=5EA3BC5E",
                            "username": "dianeducharme112"
                        },
                        "text": "@hoevinc bonjour",
                        "viewer_has_liked": false
                    }
                },
                {
                    "node": {
                        "created_at": 1573293724,
                        "did_report_as_spam": false,
                        "edge_liked_by": {
                            "count": 0
                        },
                        "id": "17869650517514523",
                        "owner": {
                            "id": "7086951195",
                            "is_verified": false,
                            "profile_pic_url": "https://scontent-cdt1-1.cdninstagram.com/v/t51.2885-19/s150x150/27574375_206169513267139_1668992658791464960_n.jpg?_nc_ht=scontent-cdt1-1.cdninstagram.com&_nc_ohc=FhXE1ziMhk8AX-6-a__&oh=e8ab4c23adaf2d08a4b942fc52246a42&oe=5E97EE7A",
                            "username": "clidierekoczwara"
                        },
                        "text": "Bonjour chef #je voulais vous demander si pour la mousse au chocolat je peux la faire dans un symphony? Merci \ud83d\ude4f",
                        "viewer_has_liked": false
                    }
                }
            ]
        },
        "edge_media_preview_like": {
            "count": 8266,
            "edges": []
        },
        "edge_media_to_caption": {
            "edges": [
                {
                    "node": {
                        "text": "Nouvelle vid\u00e9o Youtube ! Ma recette de Brownie et mousse au chocolat est disponible sur ma cha\u00eene Youtube \ud83c\udfa5\n\nN'oubliez pas de me partager vos r\u00e9sultats sur le #programmementor. \u2800\n#recette #programmementor #video #cuisine #youtube #brownie #mousseauchocolat #dessert #recetteenfant #recettefacile #recetterapide #philippeetchebest"
                    }
                }
            ]
        },
        "edge_media_to_comment": {
            "count": 57
        },
        "edge_media_to_parent_comment": {
            "count": 57,
            "edges": [
                {
                    "node": {
                        "created_at": 1572089866,
                        "did_report_as_spam": false,
                        "edge_liked_by": {
                            "count": 0
                        },
                        "edge_threaded_comments": {
                            "count": 0,
                            "edges": [],
                            "page_info": {
                                "end_cursor": null,
                                "has_next_page": false
                            }
                        },
                        "id": "17856482200600723",
                        "owner": {
                            "id": "584876874",
                            "is_verified": false,
                            "profile_pic_url": "https://scontent-cdt1-1.cdninstagram.com/v/t51.2885-19/s150x150/80349486_1167627940294663_8241074206935089152_n.jpg?_nc_ht=scontent-cdt1-1.cdninstagram.com&_nc_ohc=uI1S6eMawWYAX_LZVrq&oh=de0edfa67c61df6a5f0a18d474b34d6d&oe=5E9E27A8",
                            "username": "oumaimaouchane"
                        },
                        "text": "@easycooking1304",
                        "viewer_has_liked": false
                    }
                },
                {
                    "node": {
                        "created_at": 1572090137,
                        "did_report_as_spam": false,
                        "edge_liked_by": {
                            "count": 4
                        },
                        "edge_threaded_comments": {
                            "count": 1,
                            "edges": [
                                {
                                    "node": {
                                        "created_at": 1572192278,
                                        "did_report_as_spam": false,
                                        "edge_liked_by": {
                                            "count": 1
                                        },
                                        "id": "18060917143198463",
                                        "owner": {
                                            "id": "8969398032",
                                            "is_verified": false,
                                            "profile_pic_url": "https://scontent-cdt1-1.cdninstagram.com/v/t51.2885-19/s150x150/66624588_681147662391178_3068104463353905152_n.jpg?_nc_ht=scontent-cdt1-1.cdninstagram.com&_nc_ohc=z-H2zdJFRacAX8WTNwf&oh=c3a2106c76ae1171957099754dca326e&oe=5EA7EBF2",
                                            "username": "f11iax"
                                        },
                                        "text": "je confirme et je n aime pas trop le chocolat non plus",
                                        "viewer_has_liked": false
                                    }
                                }
                            ],
                            "page_info": {
                                "end_cursor": null,
                                "has_next_page": false
                            }
                        },
                        "id": "18088973908107711",
                        "owner": {
                            "id": "3543661574",
                            "is_verified": false,
                            "profile_pic_url": "https://scontent-cdt1-1.cdninstagram.com/v/t51.2885-19/s150x150/13741212_1195016360570514_1064998020_a.jpg?_nc_ht=scontent-cdt1-1.cdninstagram.com&_nc_ohc=UElnP5GVCREAX80YCHn&oh=026b670e9990f46240feb1ba1e82be09&oe=5E9BC4F2",
                            "username": "agnesbatouxlemega"
                        },
                        "text": "D\u00e9sol\u00e9e mais je ne suis pas fan de la mousse au chocolat mais par contre je suis FAN de vous Mr Etchebest \ud83d\udc93\ud83d\udc93\ud83d\udc93 Mais qui ne l'est pas !!!! Sous vos airs de \"colosse s\u00e9v\u00e8re\" vous avez un petit c\u0153ur qui bat \ud83d\udc93Vous \u00eates tr\u00e8s sensible ! H\u00e2te de regarder l'\u00e9mission ! Bon dimanche ensoleill\u00e9 \ud83c\udf1e\ud83c\udf1e\ud83c\udf1e",
                        "viewer_has_liked": false
                    }
                },
                {
                    "node": {
                        "created_at": 1572091241,
                        "did_report_as_spam": false,
                        "edge_liked_by": {
                            "count": 2
                        },
                        "edge_threaded_comments": {
                            "count": 0,
                            "edges": [],
                            "page_info": {
                                "end_cursor": null,
                                "has_next_page": false
                            }
                        },
                        "id": "17863266943542048",
                        "owner": {
                            "id": "49885580",
                            "is_verified": false,
                            "profile_pic_url": "https://scontent-cdt1-1.cdninstagram.com/v/t51.2885-19/11311560_161369104198023_1024863558_a.jpg?_nc_ht=scontent-cdt1-1.cdninstagram.com&_nc_ohc=hJTwgmGwFKcAX9ViHO-&oh=82fbf0ae1536fe8c3be1709205e6852b&oe=5EB41B35",
                            "username": "gouacka"
                        },
                        "text": "Super recette! Merci pour les conseils \ud83d\ude00",
                        "viewer_has_liked": false
                    }
                },
                {
                    "node": {
                        "created_at": 1572093212,
                        "did_report_as_spam": false,
                        "edge_liked_by": {
                            "count": 0
                        },
                        "edge_threaded_comments": {
                            "count": 0,
                            "edges": [],
                            "page_info": {
                                "end_cursor": null,
                                "has_next_page": false
                            }
                        },
                        "id": "17847874852698491",
                        "owner": {
                            "id": "21308721599",
                            "is_verified": false,
                            "profile_pic_url": "https://scontent-cdt1-1.cdninstagram.com/v/t51.2885-19/s150x150/72792135_745506579603698_971057917685923840_n.jpg?_nc_ht=scontent-cdt1-1.cdninstagram.com&_nc_ohc=lLQSGBusUQoAX9ehSET&oh=5241f5ce56c536289543ad8eee19c7d9&oe=5EA604B4",
                            "username": "franci6503"
                        },
                        "text": "\ud83d\udc4f\ud83d\udc4f\ud83d\ude0d",
                        "viewer_has_liked": false
                    }
                },
                {
                    "node": {
                        "created_at": 1572094928,
                        "did_report_as_spam": false,
                        "edge_liked_by": {
                            "count": 1
                        },
                        "edge_threaded_comments": {
                            "count": 2,
                            "edges": [
                                {
                                    "node": {
                                        "created_at": 1572100396,
                                        "did_report_as_spam": false,
                                        "edge_liked_by": {
                                            "count": 0
                                        },
                                        "id": "18068091577166917",
                                        "owner": {
                                            "id": "293256336",
                                            "is_verified": false,
                                            "profile_pic_url": "https://scontent-cdt1-1.cdninstagram.com/v/t51.2885-19/s150x150/70309953_442835593304124_2470072482619457536_n.jpg?_nc_ht=scontent-cdt1-1.cdninstagram.com&_nc_ohc=ww51ulFRJG8AX_xsu28&oh=fc7790595c126ba2c5db4c9acbba6012&oe=5EA8FF85",
                                            "username": "ya_wlsry"
                                        },
                                        "text": "@latzim33 hein ????",
                                        "viewer_has_liked": false
                                    }
                                },
                                {
                                    "node": {
                                        "created_at": 1572108418,
                                        "did_report_as_spam": false,
                                        "edge_liked_by": {
                                            "count": 0
                                        },
                                        "id": "17847675343708354",
                                        "owner": {
                                            "id": "13069019136",
                                            "is_verified": false,
                                            "profile_pic_url": "https://scontent-cdt1-1.cdninstagram.com/v/t51.2885-19/s150x150/67098486_369196023981303_5843552453613584384_n.jpg?_nc_ht=scontent-cdt1-1.cdninstagram.com&_nc_ohc=0YUrL9pUj-EAX_i-o9Y&oh=bb607306304f58507eed131b2d4f1cb3&oe=5E8F62A0",
                                            "username": "latzim33"
                                        },
                                        "text": "@ya_wlsry c\u2019\u00e9tait une blague",
                                        "viewer_has_liked": false
                                    }
                                }
                            ],
                            "page_info": {
                                "end_cursor": null,
                                "has_next_page": false
                            }
                        },
                        "id": "17844584635741771",
                        "owner": {
                            "id": "13069019136",
                            "is_verified": false,
                            "profile_pic_url": "https://scontent-cdt1-1.cdninstagram.com/v/t51.2885-19/s150x150/67098486_369196023981303_5843552453613584384_n.jpg?_nc_ht=scontent-cdt1-1.cdninstagram.com&_nc_ohc=0YUrL9pUj-EAX_i-o9Y&oh=bb607306304f58507eed131b2d4f1cb3&oe=5E8F62A0",
                            "username": "latzim33"
                        },
                        "text": "@ya_wlsry kestu fais sur la photo??",
                        "viewer_has_liked": false
                    }
                },
                {
                    "node": {
                        "created_at": 1572104545,
                        "did_report_as_spam": false,
                        "edge_liked_by": {
                            "count": 0
                        },
                        "edge_threaded_comments": {
                            "count": 0,
                            "edges": [],
                            "page_info": {
                                "end_cursor": null,
                                "has_next_page": false
                            }
                        },
                        "id": "18010639582251933",
                        "owner": {
                            "id": "8132799125",
                            "is_verified": false,
                            "profile_pic_url": "https://scontent-cdt1-1.cdninstagram.com/v/t51.2885-19/s150x150/75458019_495282737759607_2325504905638313984_n.jpg?_nc_ht=scontent-cdt1-1.cdninstagram.com&_nc_ohc=hnWCEqvEDfEAX9UF7fL&oh=aa914d7d10bd43c26259c4324e7716e6&oe=5EAEEB8E",
                            "username": "arnaudmombo11"
                        },
                        "text": "Tr\u00e8s bon cuisinier",
                        "viewer_has_liked": false
                    }
                },
                {
                    "node": {
                        "created_at": 1572105678,
                        "did_report_as_spam": false,
                        "edge_liked_by": {
                            "count": 1
                        },
                        "edge_threaded_comments": {
                            "count": 0,
                            "edges": [],
                            "page_info": {
                                "end_cursor": null,
                                "has_next_page": false
                            }
                        },
                        "id": "17862360769552466",
                        "owner": {
                            "id": "4876655991",
                            "is_verified": false,
                            "profile_pic_url": "https://scontent-cdt1-1.cdninstagram.com/v/t51.2885-19/s150x150/17596827_791570524352557_615540152923586560_a.jpg?_nc_ht=scontent-cdt1-1.cdninstagram.com&_nc_ohc=By4gQMPS0fAAX9-uw61&oh=3338205bc36ad00f299b167d03fece78&oe=5E983825",
                            "username": "patisserie6035"
                        },
                        "text": "Quelle bienveillance dans ce regard et ce geste \ud83d\udc4d\ud83d\udc4fvous ne pouvez pas vous cloner ? \ud83d\ude18",
                        "viewer_has_liked": false
                    }
                },
                {
                    "node": {
                        "created_at": 1572106951,
                        "did_report_as_spam": false,
                        "edge_liked_by": {
                            "count": 0
                        },
                        "edge_threaded_comments": {
                            "count": 0,
                            "edges": [],
                            "page_info": {
                                "end_cursor": null,
                                "has_next_page": false
                            }
                        },
                        "id": "17901833365378926",
                        "owner": {
                            "id": "13480808028",
                            "is_verified": false,
                            "profile_pic_url": "https://scontent-cdt1-1.cdninstagram.com/v/t51.2885-19/s150x150/66428591_436585273852981_1721964861274980352_n.jpg?_nc_ht=scontent-cdt1-1.cdninstagram.com&_nc_ohc=noyGa2TLP4wAX9WpzzD&oh=8870ca40f4215318cd3f9a3e2dd3d8a7&oe=5EACF8F7",
                            "username": "babettemagot"
                        },
                        "text": "Brownie, mousse au chocolat....stop arr\u00eater...j'ai d\u00e9j\u00e0 pris un kg..rien quand \u00e9crivant ce message\ud83d\ude09\ud83e\udd18\ud83d\ude18",
                        "viewer_has_liked": false
                    }
                },
                {
                    "node": {
                        "created_at": 1572107185,
                        "did_report_as_spam": false,
                        "edge_liked_by": {
                            "count": 0
                        },
                        "edge_threaded_comments": {
                            "count": 1,
                            "edges": [
                                {
                                    "node": {
                                        "created_at": 1573109340,
                                        "did_report_as_spam": false,
                                        "edge_liked_by": {
                                            "count": 0
                                        },
                                        "id": "17849526832696850",
                                        "owner": {
                                            "id": "23233786449",
                                            "is_verified": false,
                                            "profile_pic_url": "https://scontent-cdt1-1.cdninstagram.com/v/t51.2885-19/s150x150/74607448_2429343810658964_7115666447510011904_n.jpg?_nc_ht=scontent-cdt1-1.cdninstagram.com&_nc_ohc=xx8Xypt_BS8AX8QdCme&oh=4a94c4f4a39c9f75ebc67617cc28ea57&oe=5EA3BC5E",
                                            "username": "dianeducharme112"
                                        },
                                        "text": "@hoevinc bonjour",
                                        "viewer_has_liked": false
                                    }
                                }
                            ],
                            "page_info": {
                                "end_cursor": null,
                                "has_next_page": false
                            }
                        },
                        "id": "18098401729076104",
                        "owner": {
                            "id": "8263541758",
                            "is_verified": false,
                            "profile_pic_url": "https://scontent-cdt1-1.cdninstagram.com/v/t51.2885-19/s150x150/36938017_347461069123343_1768960290348597248_n.jpg?_nc_ht=scontent-cdt1-1.cdninstagram.com&_nc_ohc=06JY6fQdVG0AX8CH_gR&oh=20b7faa6d8a891af3f070505f9ba686d&oe=5E98CBB9",
                            "username": "hoevinc"
                        },
                        "text": "\ud83d\udc4d",
                        "viewer_has_liked": false
                    }
                },
                {
                    "node": {
                        "created_at": 1572112396,
                        "did_report_as_spam": false,
                        "edge_liked_by": {
                            "count": 2
                        },
                        "edge_threaded_comments": {
                            "count": 0,
                            "edges": [],
                            "page_info": {
                                "end_cursor": null,
                                "has_next_page": false
                            }
                        },
                        "id": "18090016672097410",
                        "owner": {
                            "id": "4248949062",
                            "is_verified": false,
                            "profile_pic_url": "https://scontent-cdt1-1.cdninstagram.com/v/t51.2885-19/s150x150/28764744_960792564091585_5141736281843171328_n.jpg?_nc_ht=scontent-cdt1-1.cdninstagram.com&_nc_ohc=Up7CAVxi7-oAX8jjXO3&oh=1f724fac6f6aa5c6e8d633e7be4c18cb&oe=5EA06153",
                            "username": "briantochantal"
                        },
                        "text": "\ud83d\ude0a\u2764\ufe0f\ud83d\udc4f\ud83c\udffc\ud83d\udc4f\ud83c\udffc\ud83d\udc4f\ud83c\udffc\ud83d\udc4d\ud83d\udc4d",
                        "viewer_has_liked": false
                    }
                },
                {
                    "node": {
                        "created_at": 1572113809,
                        "did_report_as_spam": false,
                        "edge_liked_by": {
                            "count": 1
                        },
                        "edge_threaded_comments": {
                            "count": 1,
                            "edges": [
                                {
                                    "node": {
                                        "created_at": 1572114276,
                                        "did_report_as_spam": false,
                                        "edge_liked_by": {
                                            "count": 0
                                        },
                                        "id": "17884870918441359",
                                        "owner": {
                                            "id": "279869131",
                                            "is_verified": false,
                                            "profile_pic_url": "https://scontent-cdt1-1.cdninstagram.com/v/t51.2885-19/s150x150/79836295_572390303537811_687954250721918976_n.jpg?_nc_ht=scontent-cdt1-1.cdninstagram.com&_nc_ohc=9qDcGqJsNR0AX-1fqVC&oh=af6f52e859de6984ce0f1ad6870d3876&oe=5EB09D79",
                                            "username": "leokharfan"
                                        },
                                        "text": "@leakharfan \ud83e\udd24\ud83d\ude0d",
                                        "viewer_has_liked": false
                                    }
                                }
                            ],
                            "page_info": {
                                "end_cursor": null,
                                "has_next_page": false
                            }
                        },
                        "id": "17899703503382342",
                        "owner": {
                            "id": "234286003",
                            "is_verified": false,
                            "profile_pic_url": "https://scontent-cdt1-1.cdninstagram.com/v/t51.2885-19/s150x150/72449170_466744580595993_8841800184431116288_n.jpg?_nc_ht=scontent-cdt1-1.cdninstagram.com&_nc_ohc=tJySq6RLjegAX84vTlz&oh=6a43631c8c7e876e87c2eaa0d8219b6c&oe=5E98DEEF",
                            "username": "leakharfan"
                        },
                        "text": "Brownie et mousse au chocolat, le vrai combo pour moi \u00e7a @leokharfan",
                        "viewer_has_liked": false
                    }
                },
                {
                    "node": {
                        "created_at": 1572117424,
                        "did_report_as_spam": false,
                        "edge_liked_by": {
                            "count": 1
                        },
                        "edge_threaded_comments": {
                            "count": 0,
                            "edges": [],
                            "page_info": {
                                "end_cursor": null,
                                "has_next_page": false
                            }
                        },
                        "id": "17897282701396385",
                        "owner": {
                            "id": "1837364172",
                            "is_verified": false,
                            "profile_pic_url": "https://scontent-cdt1-1.cdninstagram.com/v/t51.2885-19/s150x150/79948176_877252619339405_5718585226175709184_n.jpg?_nc_ht=scontent-cdt1-1.cdninstagram.com&_nc_ohc=2caVTq7FYicAX_FcpAm&oh=1406989af7bc6d7b96e82d9582331ca2&oe=5E90455E",
                            "username": "andrea_gouzerhtm"
                        },
                        "text": "Magnifique",
                        "viewer_has_liked": false
                    }
                },
                {
                    "node": {
                        "created_at": 1572119390,
                        "did_report_as_spam": false,
                        "edge_liked_by": {
                            "count": 1
                        },
                        "edge_threaded_comments": {
                            "count": 0,
                            "edges": [],
                            "page_info": {
                                "end_cursor": null,
                                "has_next_page": false
                            }
                        },
                        "id": "17848861903683754",
                        "owner": {
                            "id": "9665379300",
                            "is_verified": false,
                            "profile_pic_url": "https://scontent-cdt1-1.cdninstagram.com/v/t51.2885-19/s150x150/46376442_744333742599117_3084968880074915840_n.jpg?_nc_ht=scontent-cdt1-1.cdninstagram.com&_nc_ohc=jvPCklZgnbAAX8YS8vS&oh=c54fdf3fd91407464d502bd4f453ea23&oe=5E94559D",
                            "username": "lesdinersdelea"
                        },
                        "text": "Voil\u00e0 ce qui est important c est l\u00e0 Transmission bravo",
                        "viewer_has_liked": false
                    }
                },
                {
                    "node": {
                        "created_at": 1572158323,
                        "did_report_as_spam": false,
                        "edge_liked_by": {
                            "count": 0
                        },
                        "edge_threaded_comments": {
                            "count": 0,
                            "edges": [],
                            "page_info": {
                                "end_cursor": null,
                                "has_next_page": false
                            }
                        },
                        "id": "17985521590281932",
                        "owner": {
                            "id": "11769365523",
                            "is_verified": false,
                            "profile_pic_url": "https://scontent-cdt1-1.cdninstagram.com/v/t51.2885-19/s150x150/52161755_643522549401042_4346231505954013184_n.jpg?_nc_ht=scontent-cdt1-1.cdninstagram.com&_nc_ohc=HCYsde10u0AAX_rXJ5R&oh=3243449a71b569a8a329a02544bff790&oe=5E9E8E1E",
                            "username": "jeanjacquesdespoix"
                        },
                        "text": "\u2764\ufe0f\u2764\ufe0f",
                        "viewer_has_liked": false
                    }
                },
                {
                    "node": {
                        "created_at": 1572161797,
                        "did_report_as_spam": false,
                        "edge_liked_by": {
                            "count": 0
                        },
                        "edge_threaded_comments": {
                            "count": 0,
                            "edges": [],
                            "page_info": {
                                "end_cursor": null,
                                "has_next_page": false
                            }
                        },
                        "id": "17891047210419707",
                        "owner": {
                            "id": "22590327355",
                            "is_verified": false,
                            "profile_pic_url": "https://scontent-cdt1-1.cdninstagram.com/v/t51.2885-19/s150x150/76852358_573385023232617_1653943278069874688_n.jpg?_nc_ht=scontent-cdt1-1.cdninstagram.com&_nc_ohc=El5icXUjtMYAX_I4Dk5&oh=a44d2a723b3a982f0a70a2b3b4c4a6a8&oe=5EA7BD8D",
                            "username": "nayelle.licorn"
                        },
                        "text": "\u2764\ufe0f bravo j'adore tout se que vous faites chef vous \u00eates un chef splendide",
                        "viewer_has_liked": false
                    }
                },
                {
                    "node": {
                        "created_at": 1572161886,
                        "did_report_as_spam": false,
                        "edge_liked_by": {
                            "count": 0
                        },
                        "edge_threaded_comments": {
                            "count": 0,
                            "edges": [],
                            "page_info": {
                                "end_cursor": null,
                                "has_next_page": false
                            }
                        },
                        "id": "18087792676116748",
                        "owner": {
                            "id": "22590327355",
                            "is_verified": false,
                            "profile_pic_url": "https://scontent-cdt1-1.cdninstagram.com/v/t51.2885-19/s150x150/76852358_573385023232617_1653943278069874688_n.jpg?_nc_ht=scontent-cdt1-1.cdninstagram.com&_nc_ohc=El5icXUjtMYAX_I4Dk5&oh=a44d2a723b3a982f0a70a2b3b4c4a6a8&oe=5EA7BD8D",
                            "username": "nayelle.licorn"
                        },
                        "text": "\ud83d\ude0d\u2764\ufe0f\ud83d\udc4f",
                        "viewer_has_liked": false
                    }
                },
                {
                    "node": {
                        "created_at": 1572163194,
                        "did_report_as_spam": false,
                        "edge_liked_by": {
                            "count": 1
                        },
                        "edge_threaded_comments": {
                            "count": 0,
                            "edges": [],
                            "page_info": {
                                "end_cursor": null,
                                "has_next_page": false
                            }
                        },
                        "id": "18022480201246810",
                        "owner": {
                            "id": "9168736271",
                            "is_verified": false,
                            "profile_pic_url": "https://instagram.fcdg2-1.fna.fbcdn.net/v/t51.2885-19/44884218_345707102882519_2446069589734326272_n.jpg?_nc_ht=instagram.fcdg2-1.fna.fbcdn.net&_nc_ohc=E7La52ZYFJ4AX_QOybC&oh=9fce691708399863d8945f952d1feb34&oe=5E90E8F1",
                            "username": "merline.bzh"
                        },
                        "text": "\ud83d\ude0dMerci Chef! Vous savez aller \u00e0 l'essentiel \ud83d\ude09 : le chocolat!\ud83c\udf6b Un d\u00e9lice vos recettes\ud83d\udc99",
                        "viewer_has_liked": false
                    }
                },
                {
                    "node": {
                        "created_at": 1572172702,
                        "did_report_as_spam": false,
                        "edge_liked_by": {
                            "count": 0
                        },
                        "edge_threaded_comments": {
                            "count": 0,
                            "edges": [],
                            "page_info": {
                                "end_cursor": null,
                                "has_next_page": false
                            }
                        },
                        "id": "17846667940726469",
                        "owner": {
                            "id": "4050496007",
                            "is_verified": false,
                            "profile_pic_url": "https://scontent-cdt1-1.cdninstagram.com/v/t51.2885-19/s150x150/39011815_165729300933024_4647371587429859328_n.jpg?_nc_ht=scontent-cdt1-1.cdninstagram.com&_nc_ohc=Eh8CZGaca0UAX_Pio-O&oh=b7957646443d991e4eea932c7573b14d&oe=5E98E4B6",
                            "username": "mariedecorrens"
                        },
                        "text": "Je vous appr\u00e9cie beaucoup Chef Etchebest ! Vous \u00eates the BEST \ud83d\ude0d\ud83d\ude0d\ud83d\udc8b",
                        "viewer_has_liked": false
                    }
                },
                {
                    "node": {
                        "created_at": 1572183334,
                        "did_report_as_spam": false,
                        "edge_liked_by": {
                            "count": 1
                        },
                        "edge_threaded_comments": {
                            "count": 0,
                            "edges": [],
                            "page_info": {
                                "end_cursor": null,
                                "has_next_page": false
                            }
                        },
                        "id": "17921106445338814",
                        "owner": {
                            "id": "18262238171",
                            "is_verified": false,
                            "profile_pic_url": "https://scontent-cdt1-1.cdninstagram.com/v/t51.2885-19/s150x150/67366933_483520922219808_7764711618834857984_n.jpg?_nc_ht=scontent-cdt1-1.cdninstagram.com&_nc_ohc=1ASmUSdNy-8AX8TaVVs&oh=f261dfa246e48db9b50caa5b5b45a885&oe=5E9C6018",
                            "username": "fakais_ping_pong"
                        },
                        "text": "Not better than Gordon Ramsey \ud83d\udc4c\ud83d\udc4c\ud83d\udc4c",
                        "viewer_has_liked": false
                    }
                },
                {
                    "node": {
                        "created_at": 1572203516,
                        "did_report_as_spam": false,
                        "edge_liked_by": {
                            "count": 0
                        },
                        "edge_threaded_comments": {
                            "count": 0,
                            "edges": [],
                            "page_info": {
                                "end_cursor": null,
                                "has_next_page": false
                            }
                        },
                        "id": "17849597698662730",
                        "owner": {
                            "id": "22267471449",
                            "is_verified": false,
                            "profile_pic_url": "https://scontent-cdt1-1.cdninstagram.com/v/t51.2885-19/s150x150/73423661_560841211389198_7387985786601209856_n.jpg?_nc_ht=scontent-cdt1-1.cdninstagram.com&_nc_ohc=p9O-HWbCy5MAX85qRgJ&oh=905979a11aa01d8e50df7f7e0657e7ff&oe=5E9E400C",
                            "username": "le_distingo_evry_"
                        },
                        "text": "Bonjour, nous sommes une petite brasserie \u00e0 Evry-Courcouronnes.\nNous faisons tout maison, ce qui aujourd'hui est tr\u00e8s rare pour un restaurant. Nous avons un site internet, n'h\u00e9sitez pas \u00e0 aller le voir, nous changeons notre carte toutes les semaines pour vous faire des bons petits plats \ud83c\udf72 N'h\u00e9sitez pas \u00e0 nous suivre notre page Instagram ou Facebook, pour plus de renseignements ou bien voir un peu ce que l'ont fait \ud83d\ude0b. On loue aussi la salle pour des prestations alors si vous avez besoin n'h\u00e9sitez plus, nous vous offrons la qualit\u00e9 \u00e0 un pris convenable, merci et bonne journ\u00e9e \u00e0 vous messieurs et mesdames ! \ud83d\ude09",
                        "viewer_has_liked": false
                    }
                },
                {
                    "node": {
                        "created_at": 1572513955,
                        "did_report_as_spam": false,
                        "edge_liked_by": {
                            "count": 1
                        },
                        "edge_threaded_comments": {
                            "count": 0,
                            "edges": [],
                            "page_info": {
                                "end_cursor": null,
                                "has_next_page": false
                            }
                        },
                        "id": "18027953113232141",
                        "owner": {
                            "id": "6757084680",
                            "is_verified": false,
                            "profile_pic_url": "https://scontent-cdt1-1.cdninstagram.com/v/t51.2885-19/s150x150/25025571_1840431346019758_4073154173854547968_n.jpg?_nc_ht=scontent-cdt1-1.cdninstagram.com&_nc_ohc=y5moBhvRL-UAX8Sgfnt&oh=7077c399462bfead6729bf5b04aa27eb&oe=5E95A598",
                            "username": "francoiserobaux"
                        },
                        "text": "Rhaaa une recette au chocolat !!!! Mhh je vais l'essayer mais avec du chocolat belge bien s\u00fbr ! \ud83d\ude01\ud83d\ude07\ud83c\udf6b\ud83c\udf89",
                        "viewer_has_liked": false
                    }
                },
                {
                    "node": {
                        "created_at": 1572578146,
                        "did_report_as_spam": false,
                        "edge_liked_by": {
                            "count": 0
                        },
                        "edge_threaded_comments": {
                            "count": 0,
                            "edges": [],
                            "page_info": {
                                "end_cursor": null,
                                "has_next_page": false
                            }
                        },
                        "id": "17864365072549346",
                        "owner": {
                            "id": "353485650",
                            "is_verified": false,
                            "profile_pic_url": "https://scontent-cdt1-1.cdninstagram.com/v/t51.2885-19/s150x150/52363148_920862408304857_7881221883868217344_n.jpg?_nc_ht=scontent-cdt1-1.cdninstagram.com&_nc_ohc=PNyVC-IGNb0AX9Gsa6V&oh=66eeb8704212575a216ec302b21af927&oe=5EA6C7A0",
                            "username": "mathiasthejeweler"
                        },
                        "text": "\ud83d\udc4c\ud83d\udc4c",
                        "viewer_has_liked": false
                    }
                },
                {
                    "node": {
                        "created_at": 1573079403,
                        "did_report_as_spam": false,
                        "edge_liked_by": {
                            "count": 0
                        },
                        "edge_threaded_comments": {
                            "count": 0,
                            "edges": [],
                            "page_info": {
                                "end_cursor": null,
                                "has_next_page": false
                            }
                        },
                        "id": "17853212893633483",
                        "owner": {
                            "id": "3606409737",
                            "is_verified": false,
                            "profile_pic_url": "https://scontent-cdt1-1.cdninstagram.com/v/t51.2885-19/s150x150/51403801_631994473888141_5913840602729938944_n.jpg?_nc_ht=scontent-cdt1-1.cdninstagram.com&_nc_ohc=JLz9qtT5kL0AX-SClyA&oh=fcf85c139eaff90b36fa49354bdcc846&oe=5EAA2822",
                            "username": "as_salafyah"
                        },
                        "text": "Bonsoir chef , votre recette a \u00e9t\u00e9 un franc succ\u00e8s,  simple rapide et tellement d\u00e9licieux,  merci \u00e0 vous pour ce partage et vos explications",
                        "viewer_has_liked": false
                    }
                },
                {
                    "node": {
                        "created_at": 1573293724,
                        "did_report_as_spam": false,
                        "edge_liked_by": {
                            "count": 0
                        },
                        "edge_threaded_comments": {
                            "count": 0,
                            "edges": [],
                            "page_info": {
                                "end_cursor": null,
                                "has_next_page": false
                            }
                        },
                        "id": "17869650517514523",
                        "owner": {
                            "id": "7086951195",
                            "is_verified": false,
                            "profile_pic_url": "https://scontent-cdt1-1.cdninstagram.com/v/t51.2885-19/s150x150/27574375_206169513267139_1668992658791464960_n.jpg?_nc_ht=scontent-cdt1-1.cdninstagram.com&_nc_ohc=FhXE1ziMhk8AX-6-a__&oh=e8ab4c23adaf2d08a4b942fc52246a42&oe=5E97EE7A",
                            "username": "clidierekoczwara"
                        },
                        "text": "Bonjour chef #je voulais vous demander si pour la mousse au chocolat je peux la faire dans un symphony? Merci \ud83d\ude4f",
                        "viewer_has_liked": false
                    }
                }
            ],
            "page_info": {
                "end_cursor": "QVFCT3BqNlo2N045RkVSZGY1aFVYcmFEWG1SUmxKQU9VS3hfRTdaSGNySUdLeWJ1UEVnRElPZG80VTl6dXdnNW9qNkF1Zm1CSV9YdkxWUHFwRHplUUVnTw==",
                "has_next_page": true
            }
        },
        "edge_media_to_sponsor_user": {
            "edges": []
        },
        "edge_media_to_tagged_user": {
            "edges": []
        },
        "edge_web_media_to_related_media": {
            "edges": []
        },
        "fact_check_information": null,
        "fact_check_overall_rating": null,
        "gating_info": null,
        "has_ranked_comments": false,
        "id": "2163063982292831852",
        "is_ad": false,
        "is_video": false,
        "location": null,
        "media_preview": "ACoqts4QFm4A5JqC3uHmG4rsXOBnO769MU25k2/KfukY5wRz7dc/pRHIiIF3g7Rg85PHsOTx/wDWpNvoUvMuZGQDxnNRqHyRg9eMd8/y/GplVVUSFgynkY6H86vqMfXrQ1cE7GFcmaHYmCobjcOfwPoatf2JGerNWo6LKpU8g/5/Q1gtqsqEqcZXg/hxQSQykPcRqfVc/nW+beIfPsXIB52jNZccXltvHz7Tk5HI7Z+mOD6da0Q+9SWPAGeOM5yMHv2ouO3UwbM78KegP5AnNdF56AgE8np1rDhi3XBxwqjkeuBgVrrbRkYOSG7EnHr/ADou3sGi0LQBBPpXJ3RTzn6ffbsPU1ravNJBCChxlgpPfGD0P4Vy++mI6/TomEe4nqMD/wCv9On0qkZ0WQq2cA4wozznpnPP5Vp2H+r/AM+grm5eHc99x5/GofQuPU2lBSV3x8smOO4wPyx9CakF4kZKNnI+n+Nc4ZXVtqswXI4BOPyroEUfZhx/yyJ/Hnn60rsLIo39wt3EcBtisDuwMZ5Azz71kGAjjDcV0kyL5AOBlojnjr8nf1rKidti8noO/tVNkn//2Q==",
        "owner": {
            "biography": "Chef \u00e9toil\u00e9 et Meilleur Ouvrier de France, qui ne l\u00e2che rien.",
            "blocked_by_viewer": false,
            "business_category_name": "Creators & Celebrities",
            "connected_fb_page": null,
            "country_block": false,
            "edge_felix_video_timeline": {
                "count": 0,
                "edges": [],
                "page_info": {
                    "end_cursor": null,
                    "has_next_page": false
                }
            },
            "edge_follow": {
                "count": 33
            },
            "edge_followed_by": {
                "count": 437497
            },
            "edge_mutual_followed_by": {
                "count": 0,
                "edges": []
            },
            "external_url": "https://youtu.be/V77ZKMXKCQ4",
            "external_url_linkshimmed": "https://l.instagram.com/?u=https%3A%2F%2Fyoutu.be%2FV77ZKMXKCQ4&e=ATPQny6JfY8LYn3nQSseDXc5aYRxKQD_phwp_EImK9HBoRRR3EdNN-pIOmhfx-xxTh6L7kpL",
            "followed_by_viewer": false,
            "follows_viewer": false,
            "full_name": "Philippe Etchebest",
            "has_blocked_viewer": false,
            "has_channel": false,
            "has_requested_viewer": false,
            "highlight_reel_count": 6,
            "id": "4361481115",
            "is_business_account": true,
            "is_joined_recently": false,
            "is_private": false,
            "is_verified": true,
            "profile_pic_url": "https://scontent-cdt1-1.cdninstagram.com/v/t51.2885-19/s150x150/42852299_350041922431161_8340776362268688384_n.jpg?_nc_ht=scontent-cdt1-1.cdninstagram.com&_nc_ohc=DabRF9e7a4sAX_sr2Sy&oh=a5010140fa2d5f625fa44390ec412dd6&oe=5E93F46C",
            "profile_pic_url_hd": "https://scontent-cdt1-1.cdninstagram.com/v/t51.2885-19/s320x320/42852299_350041922431161_8340776362268688384_n.jpg?_nc_ht=scontent-cdt1-1.cdninstagram.com&_nc_ohc=DabRF9e7a4sAX_sr2Sy&oh=1d81a7743c3b322c21dae474643779df&oe=5E92F09C",
            "requested_by_viewer": false,
            "username": "chef.etchebest"
        },
        "shortcode": "B4EvztDAY5s",
        "taken_at_timestamp": 1572077342,
        "thumbnail_resources": [
            {
                "config_height": 150,
                "config_width": 150,
                "src": "https://scontent-cdt1-1.cdninstagram.com/v/t51.2885-15/e15/s150x150/72549021_1414349085380197_1862529061723404970_n.jpg?_nc_ht=scontent-cdt1-1.cdninstagram.com&_nc_cat=101&_nc_ohc=aZJw_96Wy2UAX_V4oVv&oh=891c412c45629c41a69ca5a0cf1e0697&oe=5E9DC4AB"
            },
            {
                "config_height": 240,
                "config_width": 240,
                "src": "https://scontent-cdt1-1.cdninstagram.com/v/t51.2885-15/e15/s240x240/72549021_1414349085380197_1862529061723404970_n.jpg?_nc_ht=scontent-cdt1-1.cdninstagram.com&_nc_cat=101&_nc_ohc=aZJw_96Wy2UAX_V4oVv&oh=af49f56aa3eb4bb73009b2491ab02e64&oe=5E8D98AD"
            },
            {
                "config_height": 320,
                "config_width": 320,
                "src": "https://scontent-cdt1-1.cdninstagram.com/v/t51.2885-15/e15/s320x320/72549021_1414349085380197_1862529061723404970_n.jpg?_nc_ht=scontent-cdt1-1.cdninstagram.com&_nc_cat=101&_nc_ohc=aZJw_96Wy2UAX_V4oVv&oh=afde7d45d70f8e4abb1e93de6958253f&oe=5EAD43D3"
            },
            {
                "config_height": 480,
                "config_width": 480,
                "src": "https://scontent-cdt1-1.cdninstagram.com/v/t51.2885-15/e15/s480x480/72549021_1414349085380197_1862529061723404970_n.jpg?_nc_ht=scontent-cdt1-1.cdninstagram.com&_nc_cat=101&_nc_ohc=aZJw_96Wy2UAX_V4oVv&oh=1658a8997932b3b32ae0a76392de0686&oe=5EAB5094"
            },
            {
                "config_height": 640,
                "config_width": 640,
                "src": "https://scontent-cdt1-1.cdninstagram.com/v/t51.2885-15/e15/s640x640/72549021_1414349085380197_1862529061723404970_n.jpg?_nc_ht=scontent-cdt1-1.cdninstagram.com&_nc_cat=101&_nc_ohc=aZJw_96Wy2UAX_V4oVv&oh=cded10e99717ad8b9c19ab9a9fad0d18&oe=5E987B68"
            }
        ],
        "thumbnail_src": "https://scontent-cdt1-1.cdninstagram.com/v/t51.2885-15/e15/s640x640/72549021_1414349085380197_1862529061723404970_n.jpg?_nc_ht=scontent-cdt1-1.cdninstagram.com&_nc_cat=101&_nc_ohc=aZJw_96Wy2UAX_V4oVv&oh=cded10e99717ad8b9c19ab9a9fad0d18&oe=5E987B68",
        "tracking_token": "eyJ2ZXJzaW9uIjo1LCJwYXlsb2FkIjp7ImlzX2FuYWx5dGljc190cmFja2VkIjp0cnVlLCJ1dWlkIjoiZWFmMjZiYTY0ZjJjNDI5Zjk4NzgyYTc4MjAxMmVkMmMyMTYzMDYzOTgyMjkyODMxODUyIn0sInNpZ25hdHVyZSI6IiJ9",
        "viewer_can_reshare": true,
        "viewer_has_liked": false,
        "viewer_has_saved": false,
        "viewer_has_saved_to_collection": false,
        "viewer_in_photo_of_you": false
    }
}